greenlet/__init__.py
greenlet/_greenlet.cpython-312.so
greenlet/platform/__init__.py
greenlet/platform/setup_switch_x64_masm.cmd
greenlet/platform/switch_aarch64_gcc.h
greenlet/platform/switch_alpha_unix.h
greenlet/platform/switch_amd64_unix.h
greenlet/platform/switch_arm32_gcc.h
greenlet/platform/switch_arm32_ios.h
greenlet/platform/switch_arm64_masm.asm
greenlet/platform/switch_arm64_masm.obj
greenlet/platform/switch_arm64_msvc.h
greenlet/platform/switch_csky_gcc.h
greenlet/platform/switch_loongarch64_linux.h
greenlet/platform/switch_m68k_gcc.h
greenlet/platform/switch_mips_unix.h
greenlet/platform/switch_ppc64_aix.h
greenlet/platform/switch_ppc64_linux.h
greenlet/platform/switch_ppc_aix.h
greenlet/platform/switch_ppc_linux.h
greenlet/platform/switch_ppc_macosx.h
greenlet/platform/switch_ppc_unix.h
greenlet/platform/switch_riscv_unix.h
greenlet/platform/switch_s390_unix.h
greenlet/platform/switch_sh_gcc.h
greenlet/platform/switch_sparc_sun_gcc.h
greenlet/platform/switch_x32_unix.h
greenlet/platform/switch_x64_masm.asm
greenlet/platform/switch_x64_masm.obj
greenlet/platform/switch_x64_msvc.h
greenlet/platform/switch_x86_msvc.h
greenlet/platform/switch_x86_unix.h
greenlet/tests/__init__.py
greenlet/tests/_test_extension.c
greenlet/tests/_test_extension.cpython-312.so
greenlet/tests/_test_extension_cpp.cpp
greenlet/tests/_test_extension_cpp.cpython-312.so
greenlet/tests/fail_clearing_run_switches.py
greenlet/tests/fail_cpp_exception.py
greenlet/tests/fail_initialstub_already_started.py
greenlet/tests/fail_slp_switch.py
greenlet/tests/fail_switch_three_greenlets.py
greenlet/tests/fail_switch_three_greenlets2.py
greenlet/tests/fail_switch_two_greenlets.py
greenlet/tests/leakcheck.py
greenlet/tests/test_contextvars.py
greenlet/tests/test_cpp.py
greenlet/tests/test_extension_interface.py
greenlet/tests/test_gc.py
greenlet/tests/test_generator.py
greenlet/tests/test_generator_nested.py
greenlet/tests/test_greenlet.py
greenlet/tests/test_greenlet_trash.py
greenlet_qpython-3.1.1.4.dist-info/METADATA
greenlet_qpython-3.1.1.4.dist-info/WHEEL
greenlet_qpython-3.1.1.4.dist-info/top_level.txt
greenlet_qpython-3.1.1.4.dist-info/RECORD
